{
    "products": [
        {"id":1,"nombre":"Nike Air Max 90 - Hombre","categoria":"Hombres","descripcion":"Tenis clásicos Nike Air Max 90 con tecnología de amortiguación visible.","image":"https://via.placeholder.com/500/00bfa5/FFFFFF?text=Nike+Air+Max+90","precio":150,"tipo":"Zapatillas Deportivas"},
        {"id":2,"nombre":"Adidas Ultra Boost - Mujer","categoria":"Mujeres","descripcion":"Zapatillas deportivas Adidas Ultra Boost con tecnología de espuma reactiva.","image":"https://via.placeholder.com/500/00bfa5/FFFFFF?text=Adidas+Ultra+Boost","precio":160,"tipo":"Zapatillas Deportivas"},
        {"id":3,"nombre":"Puma RS-X Pulses - Hombre","categoria":"Hombres","descripcion":"Tenis Puma RS-X con diseño futurista y tecnología de espuma amortiguante.","image":"https://via.placeholder.com/500/00bfa5/FFFFFF?text=Puma+RS-X","precio":120,"tipo":"Zapatillas Deportivas"},
        {"id":4,"nombre":"Converse Chuck Taylor All Star - Unisex","categoria":"Hombres","descripcion":"Clásicos tenis Converse con diseño icónico de lona.","image":"https://via.placeholder.com/500/00bfa5/FFFFFF?text=Converse","precio":65,"tipo":"Zapatillas Urbanas"},
        {"id":5,"nombre":"New Balance 574 - Mujer","categoria":"Mujeres","descripcion":"Zapatillas New Balance 574 con comodidad excepcional y estilo clásico.","image":"https://via.placeholder.com/500/00bfa5/FFFFFF?text=New+Balance+574","precio":130,"tipo":"Zapatillas Deportivas"},
        {"id":6,"nombre":"ASICS Gel-Lyte III - Hombre","categoria":"Hombres","descripcion":"Tenis ASICS Gel-Lyte III con tecnología de gel. Ideal para running.","image":"https://via.placeholder.com/500/00bfa5/FFFFFF?text=ASICS+Gel-Lyte","precio":140,"tipo":"Zapatillas Deportivas"},
        {"id":7,"nombre":"Reebok Classics Leather - Mujer","categoria":"Mujeres","descripcion":"Zapatillas Reebok Classics de cuero genuino con estilo vintage.","image":"https://via.placeholder.com/500/00bfa5/FFFFFF?text=Reebok+Classics","precio":95,"tipo":"Zapatillas Deportivas"},
        {"id":8,"nombre":"Saucony Jazz Original - Unisex","categoria":"Hombres","descripcion":"Tenis vintage Saucony Jazz con diseño retro y construcción resistente.","image":"https://via.placeholder.com/500/00bfa5/FFFFFF?text=Saucony+Jazz","precio":75,"tipo":"Zapatillas Urbanas"},
        {"id":9,"nombre":"Vans Old Skool - Mujer","categoria":"Mujeres","descripcion":"Tenis Vans Old Skool con banda lateral característica.","image":"https://via.placeholder.com/500/00bfa5/FFFFFF?text=Vans+Old+Skool","precio":70,"tipo":"Zapatillas Urbanas"},
        {"id":10,"nombre":"Nike Revolution 6 - Niño","categoria":"Niños","descripcion":"Zapatillas Nike para niños con tecnología de amortiguación ligera.","image":"https://via.placeholder.com/500/00bfa5/FFFFFF?text=Nike+Revolution+6","precio":55,"tipo":"Zapatillas Infantiles"},
        {"id":11,"nombre":"Adidas Stan Smith - Unisex","categoria":"Mujeres","descripcion":"Clásicos tenis Adidas Stan Smith con cuero premium.","image":"https://via.placeholder.com/500/00bfa5/FFFFFF?text=Adidas+Stan+Smith","precio":110,"tipo":"Zapatillas Deportivas"},
        {"id":12,"nombre":"Nike Court Legacy - Hombre","categoria":"Hombres","descripcion":"Tenis Nike con inspiración en diseños de tenis clásicos.","image":"https://via.placeholder.com/500/00bfa5/FFFFFF?text=Nike+Court+Legacy","precio":85,"tipo":"Zapatillas Deportivas"},
        {"id":13,"nombre":"Puma Future Rider - Niño","categoria":"Niños","descripcion":"Zapatillas Puma para niños con diseño moderno y colores vibrantes.","image":"https://via.placeholder.com/500/00bfa5/FFFFFF?text=Puma+Future+Rider","precio":60,"tipo":"Zapatillas Infantiles"},
        {"id":14,"nombre":"Mizuno Wave Rider - Hombre","categoria":"Hombres","descripcion":"Tenis Mizuno para running con tecnología Wave.","image":"https://via.placeholder.com/500/00bfa5/FFFFFF?text=Mizuno+Wave+Rider","precio":145,"tipo":"Zapatillas Running"},
        {"id":15,"nombre":"Skechers D'Lites - Mujer","categoria":"Mujeres","descripcion":"Zapatillas Skechers Memory Foam con máxima comodidad para todo el día.","image":"https://via.placeholder.com/500/00bfa5/FFFFFF?text=Skechers+D+Lites","precio":75,"tipo":"Zapatillas Deportivas"},
        {"id":16,"nombre":"New Balance Fresh Foam 680 - Mujer","categoria":"Mujeres","descripcion":"Zapatillas New Balance con comodidad superior.","image":"https://via.placeholder.com/500/00bfa5/FFFFFF?text=New+Balance+680","precio":100,"tipo":"Zapatillas Running"},
        {"id":17,"nombre":"Adidas NMD - Niño","categoria":"Niños","descripcion":"Zapatillas Adidas con diseño moderno y suela ondulada.","image":"https://via.placeholder.com/500/00bfa5/FFFFFF?text=Adidas+NMD","precio":90,"tipo":"Zapatillas Infantiles"},
        {"id":18,"nombre":"Nike Cortez - Mujer","categoria":"Mujeres","descripcion":"Clásicas zapatillas Nike Cortez con diseño vintage modernizado.","image":"https://via.placeholder.com/500/00bfa5/FFFFFF?text=Nike+Cortez","precio":105,"tipo":"Zapatillas Deportivas"},
        {"id":19,"nombre":"Reebok Nano X - Hombre","categoria":"Hombres","descripcion":"Tenis de entrenamiento Reebok Nano con construcción reforzada.","image":"https://via.placeholder.com/500/00bfa5/FFFFFF?text=Reebok+Nano+X","precio":155,"tipo":"Zapatillas Entrenamiento"},
        {"id":20,"nombre":"ASICS GT-2000 - Mujer","categoria":"Mujeres","descripcion":"Zapatillas ASICS para running con tecnología de estabilidad.","image":"https://via.placeholder.com/500/00bfa5/FFFFFF?text=ASICS+GT-2000","precio":165,"tipo":"Zapatillas Running"},
        {"id":21,"nombre":"Vans Authentic - Hombre","categoria":"Hombres","descripcion":"Clásicos tenis Vans Authentic con lona premium.","image":"https://via.placeholder.com/500/00bfa5/FFFFFF?text=Vans+Authentic","precio":65,"tipo":"Zapatillas Urbanas"},
        {"id":22,"nombre":"Puma Suede Classic - Mujer","categoria":"Mujeres","descripcion":"Zapatillas Puma de ante con estilo retro.","image":"https://via.placeholder.com/500/00bfa5/FFFFFF?text=Puma+Suede+Classic","precio":80,"tipo":"Zapatillas Deportivas"},
        {"id":23,"nombre":"Nike Air Force 1 - Unisex","categoria":"Hombres","descripcion":"Ícono del tenis Nike Air Force 1 con construcción de cuero genuino.","image":"https://via.placeholder.com/500/00bfa5/FFFFFF?text=Nike+Air+Force+1","precio":120,"tipo":"Zapatillas Deportivas"},
        {"id":24,"nombre":"Adidas ZX 500 - Mujer","categoria":"Mujeres","descripcion":"Zapatillas Adidas con diseño retro running.","image":"https://via.placeholder.com/500/00bfa5/FFFFFF?text=Adidas+ZX+500","precio":85,"tipo":"Zapatillas Deportivas"},
        {"id":25,"nombre":"Saucony Ride 13 - Hombre","categoria":"Hombres","descripcion":"Zapatillas Saucony para running con máxima comodidad.","image":"https://via.placeholder.com/500/00bfa5/FFFFFF?text=Saucony+Ride+13","precio":135,"tipo":"Zapatillas Running"},
        {"id":26,"nombre":"Nike LeBron 18 - Hombre","categoria":"Hombres","descripcion":"Tenis Nike diseñados para basketball con comodidad máxima.","image":"https://via.placeholder.com/500/00bfa5/FFFFFF?text=Nike+LeBron+18","precio":200,"tipo":"Zapatillas Basketball"},
        {"id":27,"nombre":"Adidas Superstar - Niño","categoria":"Niños","descripcion":"Clásicas zapatillas Adidas Superstar en versión infantil.","image":"https://via.placeholder.com/500/00bfa5/FFFFFF?text=Adidas+Superstar","precio":70,"tipo":"Zapatillas Infantiles"},
        {"id":28,"nombre":"New Balance 990v5 - Hombre","categoria":"Hombres","descripcion":"Zapatillas New Balance premium con la mejor tecnología.","image":"https://via.placeholder.com/500/00bfa5/FFFFFF?text=New+Balance+990v5","precio":185,"tipo":"Zapatillas Premium"},
        {"id":29,"nombre":"Puma RS Runbird - Mujer","categoria":"Mujeres","descripcion":"Zapatillas Puma con diseño moderno y colores llamativos.","image":"https://via.placeholder.com/500/00bfa5/FFFFFF?text=Puma+RS+Runbird","precio":110,"tipo":"Zapatillas Deportivas"}
    ]
}
